mqtt_bundle/__init__.py
mqtt_bundle/bundle.py
mqtt_bundle-2.5.dist-info/DESCRIPTION.rst
mqtt_bundle-2.5.dist-info/METADATA
mqtt_bundle-2.5.dist-info/RECORD
mqtt_bundle-2.5.dist-info/WHEEL
mqtt_bundle-2.5.dist-info/metadata.json
mqtt_bundle-2.5.dist-info/top_level.txt
