Metadata-Version: 2.0
Name: mqtt-bundle
Version: 2.5
Summary: mqtt support for applauncher
Home-page: https://github.com/applauncher-team/mqtt_bundle
Author: Alvaro Garcia Gomez
Author-email: maxpowel@gmail.com
License: UNKNOWN
Download-URL: https://github.com/applauncher-team/mqtt_bundle/archive/master.zip
Keywords: applauncher,bundle,mqtt
Platform: UNKNOWN
Classifier: Topic :: Adaptive Technologies
Classifier: Topic :: Software Development
Classifier: Topic :: System
Classifier: Topic :: Utilities
Requires-Dist: applauncher (==1.44)
Requires-Dist: paho-mqtt (==1.4.0)
